hytera_homebrew_bridge/__init__.py
hytera_homebrew_bridge/kaitai/__init__.py
hytera_homebrew_bridge/kaitai/data_delivery_states.py
hytera_homebrew_bridge/kaitai/data_transmit_protocol.py
hytera_homebrew_bridge/kaitai/datetimestring.py
hytera_homebrew_bridge/kaitai/gpsdata.py
hytera_homebrew_bridge/kaitai/homebrew.py
hytera_homebrew_bridge/kaitai/hytera_dmr_application_protocol.py
hytera_homebrew_bridge/kaitai/hytera_radio_network_protocol.py
hytera_homebrew_bridge/kaitai/hytera_simple_transport_reliability_protocol.py
hytera_homebrew_bridge/kaitai/intervalstring.py
hytera_homebrew_bridge/kaitai/ip_site_connect_heartbeat.py
hytera_homebrew_bridge/kaitai/ip_site_connect_protocol.py
hytera_homebrew_bridge/kaitai/location_protocol.py
hytera_homebrew_bridge/kaitai/mmdvm.py
hytera_homebrew_bridge/kaitai/radio_control_protocol.py
hytera_homebrew_bridge/kaitai/radio_id.py
hytera_homebrew_bridge/kaitai/radio_ip.py
hytera_homebrew_bridge/kaitai/radio_registration_service.py
hytera_homebrew_bridge/kaitai/real_time_transport_protocol.py
hytera_homebrew_bridge/kaitai/self_defined_message_protocol.py
hytera_homebrew_bridge/kaitai/telemetry_protocol.py
hytera_homebrew_bridge/kaitai/text_message_protocol.py
hytera_homebrew_bridge/lib/__init__.py
hytera_homebrew_bridge/lib/custom_bridge_datagram_protocol.py
hytera_homebrew_bridge/lib/hytera_mmdvm_translator.py
hytera_homebrew_bridge/lib/hytera_protocols.py
hytera_homebrew_bridge/lib/logging_trait.py
hytera_homebrew_bridge/lib/mmdvm_protocol.py
hytera_homebrew_bridge/lib/packet_format.py
hytera_homebrew_bridge/lib/settings.py
hytera_homebrew_bridge/lib/snmp.py
hytera_homebrew_bridge/lib/utils.py
hytera_homebrew_bridge/tests/__init__.py
hytera_homebrew_bridge/tests/common.py
hytera_homebrew_bridge/tests/hdap_single_packet.py
hytera_homebrew_bridge/tests/homebrew_single_packet.py
hytera_homebrew_bridge/tests/hrnp_single_packet.py
hytera_homebrew_bridge/tests/hrnp_test.py
hytera_homebrew_bridge/tests/hstrp_single_packet.py
hytera_homebrew_bridge-2021.2.dist-info/LICENSE
hytera_homebrew_bridge-2021.2.dist-info/METADATA
hytera_homebrew_bridge-2021.2.dist-info/NOTICE
hytera_homebrew_bridge-2021.2.dist-info/WHEEL
hytera_homebrew_bridge-2021.2.dist-info/top_level.txt
hytera_homebrew_bridge-2021.2.dist-info/RECORD
