Metadata-Version: 2.1
Name: hytera-homebrew-bridge
Version: 2021.2
Summary: Connect Hytera IPSC repeater to MMDVM system such as HBlink, DMRGateway
Home-page: https://github.com/OK-DMR/Hytera_Homebrew_Bridge
Author: Marek Sebera
Author-email: marek.sebera@gmail.com
License: AGPL-3.0
Keywords: mmdvm dmr hytera repeater ham radio repeater
Platform: UNKNOWN
Classifier: Development Status :: 3 - Alpha
Classifier: License :: OSI Approved :: GNU Affero General Public License v3 or later (AGPLv3+)
Classifier: Environment :: Console
Classifier: Topic :: Communications :: Ham Radio
Classifier: Operating System :: POSIX :: Linux
Classifier: Typing :: Typed
Classifier: Framework :: Pytest
Classifier: Framework :: Flake8
Classifier: Intended Audience :: Telecommunications Industry
Classifier: Natural Language :: English
Classifier: Programming Language :: Python :: 3.7
Requires-Python: ~=3.7
License-File: LICENSE
License-File: NOTICE
Requires-Dist: configparser (>=5.0.1)
Requires-Dist: kaitaistruct (>=0.9)
Requires-Dist: puresnmp (>=1.10.2)
Requires-Dist: asyncio (>=3.4.3)
Requires-Dist: dmr-utils3 (>=0.1.29)
Requires-Dist: bitarray (>=1.6.1)
